query_rewritor/__init__.py
query_rewritor/chatgpt_based/__init__.py
query_rewritor/chatgpt_based/query_rewritor.py
query_rewritor/chatgpt_based/synonyms_generator.py
query_rewritor/regex_based/__init__.py
query_rewritor/regex_based/query_rewritor.py
query_rewritor/regex_based/test.py
QueryRewriter-0.2.2.dist-info/METADATA
QueryRewriter-0.2.2.dist-info/WHEEL
QueryRewriter-0.2.2.dist-info/top_level.txt
QueryRewriter-0.2.2.dist-info/RECORD
