Metadata-Version: 2.1
Name: QueryRewriter
Version: 0.2.2
Author: Tinh Luong
Requires-Dist: langdetect
Requires-Dist: openai
